AminoService/__init__.py
AminoService/acm.py
AminoService/client.py
AminoService/socket.py
AminoService/sub_client.py
AminoService/lib/__init__.py
AminoService/lib/util/__init__.py
AminoService/lib/util/exceptions.py
AminoService/lib/util/headers.py
AminoService/lib/util/helpers.py
AminoService/lib/util/objects.py
AminoService-1.2.6.dist-info/METADATA
AminoService-1.2.6.dist-info/WHEEL
AminoService-1.2.6.dist-info/top_level.txt
AminoService-1.2.6.dist-info/RECORD
