Metadata-Version: 2.1
Name: AminoService
Version: 1.2.6
Summary: A library to create Amino bots and scripts
Home-page: https://github.com/innocentzero143/AminoService
Download-URL: https://github.com/innocentzero143/AminoService/archive/refs/heads/main.zip
Author: innocentzero143
Author-email: innocentzero143@gmail.com
License: MIT
Keywords: aminoapps,AminoServiceamino,amino-bot,narvii,api,python,python3,python3.x,innocent-zero
Requires-Dist: setuptools
Requires-Dist: requests
Requires-Dist: six
Requires-Dist: websockets
Requires-Dist: websocket-client ==1.3.1
Requires-Dist: aiohttp
